supertropical/__init__.py
supertropical/element.py
supertropical/matrix.py
supertropicalpy-0.1.2.dist-info/licenses/LICENSE
supertropicalpy-0.1.2.dist-info/METADATA
supertropicalpy-0.1.2.dist-info/WHEEL
supertropicalpy-0.1.2.dist-info/top_level.txt
supertropicalpy-0.1.2.dist-info/RECORD
