Metadata-Version: 2.4
Name: supertropicalpy
Version: 0.1.2
Summary: A Python package for supertropical algebra with tangible and ghost elements
Author-email: Teosofi Hidayah Agung <teosofihidayahagung@gmail.com>
License: MIT License
Project-URL: Homepage, https://github.com/TetewHeroez/supertropicalpy
Project-URL: Documentation, https://tetewhereoez.github.io/supertropicalpy
Project-URL: Repository, https://github.com/TetewHeroez/supertropicalpy
Classifier: Programming Language :: Python :: 3
Classifier: Programming Language :: Python :: 3.9
Classifier: Programming Language :: Python :: 3.10
Classifier: Programming Language :: Python :: 3.11
Classifier: Programming Language :: Python :: 3.12
Classifier: Programming Language :: Python :: 3.13
Classifier: License :: OSI Approved :: MIT License
Classifier: Operating System :: OS Independent
Classifier: Topic :: Scientific/Engineering :: Mathematics
Requires-Python: >=3.9
License-File: LICENSE
Requires-Dist: numpy>=1.20.0
Provides-Extra: dev
Requires-Dist: pytest>=7.0; extra == "dev"
Requires-Dist: pytest-cov; extra == "dev"
Requires-Dist: black; extra == "dev"
Requires-Dist: flake8; extra == "dev"
Provides-Extra: docs
Requires-Dist: sphinx>=4.0.0; extra == "docs"
Requires-Dist: sphinx-rtd-theme; extra == "docs"
Requires-Dist: nbsphinx; extra == "docs"
Requires-Dist: myst-parser; extra == "docs"
Requires-Dist: ipython; extra == "docs"
Requires-Dist: jupyter; extra == "docs"
Dynamic: license-file
